PETINA/__init__.py
PETINA/Clipping/__init__.py
PETINA/Clipping/clipping.py
PETINA/DP_Mechanisms/README.md
PETINA/DP_Mechanisms/__init__.py
PETINA/DP_Mechanisms/core.py
PETINA/Data_Conversion_Helper/__init__.py
PETINA/Data_Conversion_Helper/conversions.py
PETINA/Encoding_Pertubation/__init__.py
PETINA/Encoding_Pertubation/bit_perturbation_and_encoding.py
PETINA/examples/1_basic.py
PETINA/examples/2_Personal_data.py
PETINA/examples/3_Iris_data.py
PETINA/examples/4_ML_MNIST_No_MA.py
PETINA/examples/4_ML_MNIST_No_MA_Dynamic_Optimizer.py
PETINA/examples/5_ML_MNIST_MA_Opacus.py
PETINA/examples/5_ML_MNIST_MA_Opacus_Dynamic_Optimizer.py
PETINA/examples/6_FL_MNIST_MA_Opacus.py
PETINA/examples/6_FL_MNIST_MA_Opacus_Dynamic_Optimizer.py
PETINA/examples/README.md
PETINA/examples/validation_example/README.md
PETINA/examples/validation_example/IBM/example1.py
PETINA/examples/validation_example/smartnoise/.gitignore
PETINA/examples/validation_example/smartnoise/Example_1_Compare_Laplace_Mechanisms_Realdata copy.py
PETINA/examples/validation_example/smartnoise/Example_2_Compare_Gaussian_Mechanisms_Realdata.py
PETINA/examples/validation_example/smartnoise/d a
PETINA/examples/validation_example/smartnoise/example1.py
PETINA/examples/validation_example/smartnoise/tutorial5_PETINA_MA_Implement.py
PETINA/package/BayesianOptimization_local/__init__.py
PETINA/package/BayesianOptimization_local/bayesian_optimization.py
PETINA/package/BayesianOptimization_local/constraint.py
PETINA/package/BayesianOptimization_local/domain_reduction.py
PETINA/package/BayesianOptimization_local/event.py
PETINA/package/BayesianOptimization_local/logger.py
PETINA/package/BayesianOptimization_local/observer.py
PETINA/package/BayesianOptimization_local/target_space.py
PETINA/package/BayesianOptimization_local/util.py
PETINA/package/BayesianOptimization_local/examples/advanced-tour.ipynb
PETINA/package/BayesianOptimization_local/examples/async_optimization.py
petina-0.0.19.dist-info/METADATA
petina-0.0.19.dist-info/WHEEL
petina-0.0.19.dist-info/licenses/LICENSE
petina-0.0.19.dist-info/RECORD
