Metadata-Version: 2.4
Name: PETINA
Version: 0.0.19
Summary: This library contains a collection of privacy preservation techniques.
Project-URL: Homepage, https://github.com/ORNL/PETINA
Project-URL: Repository, https://github.com/ORNL/PETINA.git
Author-email: Olivera Kotevska <KOTEVSKAO@ORNL.GOV>
Maintainer-email: Olivera Kotevska <KOTEVSKAO@ORNL.GOV>
License-Expression: MIT
License-File: LICENSE
Keywords: federated learning,machine learning,privacy
Classifier: License :: OSI Approved :: MIT License
Classifier: Operating System :: OS Independent
Classifier: Programming Language :: Python
Requires-Python: >=3.8
Requires-Dist: colorama>=0.4.6
Requires-Dist: numpy
Requires-Dist: scikit-learn
Requires-Dist: scipy
Requires-Dist: torch
Requires-Dist: tqdm
